commitly/__init__.py
commitly/commitly.py
commitly/prompt.py
commitly/exceptions/diffEmptyException.py
commitly/exceptions/__pycache__/diffEmptyException.cpython-312.pyc
commitly-3.1.3.dist-info/LICENSE
commitly-3.1.3.dist-info/METADATA
commitly-3.1.3.dist-info/WHEEL
commitly-3.1.3.dist-info/entry_points.txt
commitly-3.1.3.dist-info/top_level.txt
commitly-3.1.3.dist-info/RECORD
