Metadata-Version: 2.1
Name: commitly
Version: 3.1.3
Summary: Generate a well-structured commit message based on staged changes
Home-page: https://github.com/Tostenn/Commitly
Author: Kouya Tosten
Author-email: kouyatosten@gmail.com
Classifier: Programming Language :: Python :: 3
Classifier: License :: OSI Approved :: MIT License
Classifier: Operating System :: OS Independent
Classifier: Intended Audience :: Developers
Classifier: Topic :: Software Development :: Version Control
Requires-Python: >=3.7
License-File: LICENSE
Requires-Dist: requests==2.32.3
